reduce/VERSION
reduce/__init__.py
reduce/file_tools.py
reduce/m_clear_attr.py
reduce/m_pre_commit.py
reduce/m_scan_png.py
reduce/main.py
reduce/util_res_read.py
reduce/util_res_xml.py
reduce/inject/HOOK_PRE_COMMIT
reduce/inject/PY_PRE_COMMIT
reduce/inject/pngquant
hydg-1.0.0.dist-info/METADATA
hydg-1.0.0.dist-info/WHEEL
hydg-1.0.0.dist-info/entry_points.txt
hydg-1.0.0.dist-info/top_level.txt
hydg-1.0.0.dist-info/RECORD
