Metadata-Version: 2.1
Name: hydg
Version: 1.0.0
Summary: a android ios png compression tool
Home-page: https://github.com/illidantao/PyHydg
Author: hdtpjhz
Author-email: hdtpjhz@163.com
License: UNKNOWN
Platform: UNKNOWN
Classifier: Programming Language :: Python :: 3
Classifier: License :: OSI Approved :: MIT License
Classifier: Operating System :: OS Independent
Requires-Python: >=3.6
